piel/__init__.py
piel/analysis/__init__.py
piel/analysis/electro_optic/__init__.py
piel/analysis/electro_optic/metrics.py
piel/analysis/electro_optic/modulation.py
piel/analysis/electronic/__init__.py
piel/analysis/electronic/gain.py
piel/analysis/electronic/metrics.py
piel/analysis/metrics/__init__.py
piel/analysis/metrics/join.py
piel/analysis/metrics/metadata.py
piel/analysis/metrics/statistics.py
piel/analysis/metrics/units.py
piel/analysis/signals/__init__.py
piel/analysis/signals/dc/__init__.py
piel/analysis/signals/dc/metrics.py
piel/analysis/signals/dc/transfer/__init__.py
piel/analysis/signals/dc/transfer/metrics.py
piel/analysis/signals/dc/transfer/power.py
piel/analysis/signals/dc/utils.py
piel/analysis/signals/frequency/__init__.py
piel/analysis/signals/frequency/core/__init__.py
piel/analysis/signals/frequency/core/extract.py
piel/analysis/signals/frequency/core/metrics.py
piel/analysis/signals/time/__init__.py
piel/analysis/signals/time/core/__init__.py
piel/analysis/signals/time/core/compose.py
piel/analysis/signals/time/core/dimension.py
piel/analysis/signals/time/core/metrics.py
piel/analysis/signals/time/core/off_state.py
piel/analysis/signals/time/core/offset.py
piel/analysis/signals/time/core/remove.py
piel/analysis/signals/time/core/split.py
piel/analysis/signals/time/core/threshold.py
piel/analysis/signals/time/core/transform.py
piel/analysis/signals/time/core/transition.py
piel/analysis/signals/time/integration/__init__.py
piel/analysis/signals/time/integration/extract_pulse_metrics.py
piel/analysis/timing/group_velocity.py
piel/base/__init__.py
piel/base/experimental/__init__.py
piel/base/experimental/experiment.py
piel/base/experimental/measurements/__init__.py
piel/base/experimental/measurements/data/__init__.py
piel/base/experimental/measurements/data/core.py
piel/base/experimental/measurements/data/experiment.py
piel/base/metrics.py
piel/base/quantity.py
piel/base/signal/__init__.py
piel/base/signal/frequency/__init__.py
piel-0.1.0.dist-info/LICENSE
piel-0.1.0.dist-info/METADATA
piel-0.1.0.dist-info/WHEEL
piel-0.1.0.dist-info/entry_points.txt
piel-0.1.0.dist-info/RECORD
