Metadata-Version: 2.3
Name: piel
Version: 0.1.0
Summary: Photonic Integrated Electronics: microservices to codesign photonics, electronics, communications, quantum, and more.
License: MIT
Keywords: piel,photonics,electronics,codesign,quantum,hardware
Author: Dario Quintero
Author-email: darioaquintero@gmail.com
Requires-Python: >=3.10,<3.12
Classifier: Development Status :: 2 - Pre-Alpha
Classifier: Intended Audience :: Science/Research
Classifier: License :: OSI Approved :: MIT License
Classifier: Natural Language :: English
Classifier: Programming Language :: Python :: 3
Classifier: Programming Language :: Python :: 3.10
Classifier: Programming Language :: Python :: 3.11
Classifier: Topic :: Scientific/Engineering
Classifier: Topic :: Scientific/Engineering :: Physics
Provides-Extra: dev
Provides-Extra: tools
Requires-Dist: Click (>=7.0)
Requires-Dist: amaranth (>=0.4.0,<0.5.0) ; extra == "tools" or extra == "dev"
Requires-Dist: amaranth-yosys (>=0.40.0.0.post94,<0.41.0) ; extra == "tools" or extra == "dev"
Requires-Dist: bokeh ; extra == "dev"
Requires-Dist: bump-my-version ; extra == "dev"
Requires-Dist: cocotb (==1.9.1) ; extra == "tools" or extra == "dev"
Requires-Dist: cookiecutter ; extra == "dev"
Requires-Dist: coverage ; extra == "dev"
Requires-Dist: devtools ; extra == "dev"
Requires-Dist: flake8 ; extra == "dev"
Requires-Dist: gdsfactory (==7.27.2) ; extra == "tools" or extra == "dev"
Requires-Dist: gplugins[schematic] (>=0.14.0,<0.15.0) ; extra == "tools" or extra == "dev"
Requires-Dist: hdl21 (>=6.0.0,<7.0.0) ; extra == "tools" or extra == "dev"
Requires-Dist: ipyevents ; extra == "dev"
Requires-Dist: ipytree ; extra == "dev"
Requires-Dist: ipywidgets (>=7.6.0,<9) ; extra == "dev"
Requires-Dist: jax (>=0.4.14,<0.5.0)
Requires-Dist: jaxlib (>=0.4.14,<0.5.0)
Requires-Dist: jaxtyping
Requires-Dist: jupyter ; extra == "dev"
Requires-Dist: jupyter-bokeh ; extra == "dev"
Requires-Dist: jupyter-core ; extra == "dev"
Requires-Dist: jupyter-packaging (>=0.7.9) ; extra == "dev"
Requires-Dist: jupyterlab (>=4.0.0,<5.0.0) ; extra == "dev"
Requires-Dist: jupytext (==1.15.0) ; extra == "dev"
Requires-Dist: kfactory[git,ipy] ; extra == "dev"
Requires-Dist: kweb (>=2.0.1,<3.0.0) ; extra == "dev"
Requires-Dist: matplotlib
Requires-Dist: myst-parser ; extra == "dev"
Requires-Dist: nbsphinx ; extra == "dev"
Requires-Dist: networkx (>=3.1,<4.0)
Requires-Dist: numpy (>=1.24.4,<2.0.0)
Requires-Dist: pandas (>=1.5.3,<2.0.0)
Requires-Dist: pandoc ; extra == "dev"
Requires-Dist: pre-commit ; extra == "dev"
Requires-Dist: pydantic (>=2.0,<3.0)
Requires-Dist: pydata-sphinx-theme (>=0.13.3) ; extra == "dev"
Requires-Dist: pytest (>=3.0) ; extra == "dev"
Requires-Dist: qutip (>=4.7,<5.0) ; extra == "tools" or extra == "dev"
Requires-Dist: ruff (==0.5.5) ; extra == "dev"
Requires-Dist: sax (==0.12.2) ; extra == "tools" or extra == "dev"
Requires-Dist: scikit-rf (>=1.1.0,<2.0.0) ; extra == "tools" or extra == "dev"
Requires-Dist: scipy (>=1.11.4,<2.0.0)
Requires-Dist: setuptools
Requires-Dist: sky130-hdl21 (>=6.0.0,<7.0.0) ; extra == "tools" or extra == "dev"
Requires-Dist: sphinx (>=7.2.1,<8.0.0) ; extra == "dev"
Requires-Dist: sphinx-autoapi ; extra == "dev"
Requires-Dist: sphinx-autobuild ; extra == "dev"
Requires-Dist: sphinx-autodoc-typehints ; extra == "dev"
Requires-Dist: sphinx-book_theme ; extra == "dev"
Requires-Dist: sphinx-copybutton (>=0.5.2) ; extra == "dev"
Requires-Dist: sphinx-gallery ; extra == "dev"
Requires-Dist: sphinx-pydantic ; extra == "dev"
Requires-Dist: sphinx-rtd-theme ; extra == "dev"
Requires-Dist: sphinx-version-warning ; extra == "dev"
Requires-Dist: tabulate ; extra == "tools" or extra == "dev"
Requires-Dist: thewalrus (>=0.20.0,<0.21.0) ; extra == "tools" or extra == "dev"
Requires-Dist: tox ; extra == "dev"
Requires-Dist: vlsirtools (>=6.0.0,<7.0.0) ; extra == "tools" or extra == "dev"
Requires-Dist: watchdog ; extra == "dev"
Requires-Dist: xarray (>=2024.1.0,<2024.10.0)
Project-URL: Homepage, https://github.com/daquintero/piel
Project-URL: Repository, https://github.com/daquintero/piel
